[
    {
        "id": 72,
        "name": "Josefa Bergnaum",
        "first_name": "Josefa",
        "profile_image": "https://via.placeholder.com/168x168.png/0055dd?text=aut",
        "background_image": "https://via.placeholder.com/850x350.png/00bbbb?text=id"
    },
    {
        "id": 4,
        "name": "Brielle Kuphal",
        "first_name": "Brielle",
        "profile_image": "https://via.placeholder.com/168x168.png/0011aa?text=mollitia",
        "background_image": "https://via.placeholder.com/850x350.png/00ff77?text=deleniti"
    },
    {
        "id": 18,
        "name": "Irma Huels",
        "first_name": "Irma",
        "profile_image": "https://via.placeholder.com/168x168.png/0011dd?text=cum",
        "background_image": "https://via.placeholder.com/850x350.png/0066aa?text=et"
    },
    {
        "id": 81,
        "name": "Marcin Witas",
        "first_name": "Marcin",
        "profile_image": "https://via.placeholder.com/168x168.png/009988?text=molestiae",
        "background_image": "https://via.placeholder.com/850x350.png/0044bb?text=sunt"
    },
    {
        "id": 35,
        "name": "Crawford Lakin",
        "first_name": "Crawford",
        "profile_image": "https://via.placeholder.com/168x168.png/00ffff?text=recusandae",
        "background_image": "https://via.placeholder.com/850x350.png/00aaaa?text=qui"
    },
    {
        "id": 29,
        "name": "Tristian Kiehn",
        "first_name": "Tristian",
        "profile_image": "https://via.placeholder.com/168x168.png/0022cc?text=in",
        "background_image": "https://via.placeholder.com/850x350.png/0011aa?text=quas"
    },
    {
        "id": 16,
        "name": "Kieran Koss",
        "first_name": "Kieran",
        "profile_image": "https://via.placeholder.com/168x168.png/00bbff?text=minus",
        "background_image": "https://via.placeholder.com/850x350.png/00ff55?text=sed"
    },
    {
        "id": 75,
        "name": "Felipa Lindgren",
        "first_name": "Felipa",
        "profile_image": "https://via.placeholder.com/168x168.png/00dd55?text=necessitatibus",
        "background_image": "https://via.placeholder.com/850x350.png/005500?text=sed"
    },
    {
        "id": 15,
        "name": "Daphney Koch",
        "first_name": "Daphney",
        "profile_image": "https://via.placeholder.com/168x168.png/0033dd?text=quaerat",
        "background_image": "https://via.placeholder.com/850x350.png/007799?text=id"
    },
    {
        "id": 1,
        "name": "Brenden O'Kon",
        "first_name": "Brenden",
        "profile_image": "https://via.placeholder.com/168x168.png/00aa55?text=inventore",
        "background_image": "https://via.placeholder.com/850x350.png/00eecc?text=commodi"
    }
]
