{
    "data": [
        {
            "friend": {
                "id": 4,
                "name": "Morris Gaylord",
                "first_name": "Morris",
                "profile_image": "https://picsum.photos/seed/62fd0b328eb89/168/168",
                "background_image": "https://picsum.photos/seed/62fd0b328eb91/850/350"
            },
            "data": { "id": 1, "count": 969, "updated_at": "20m" }
        },
        {
            "friend": {
                "id": 5,
                "name": "Modesta Barrows",
                "first_name": "Modesta",
                "profile_image": "https://picsum.photos/seed/62fd0b33f283b/168/168",
                "background_image": "https://picsum.photos/seed/62fd0b33f2840/850/350"
            },
            "data": { "id": 2, "count": 8994, "updated_at": "20m" }
        },
        {
            "friend": {
                "id": 6,
                "name": "Jeanne Moen",
                "first_name": "Jeanne",
                "profile_image": "https://picsum.photos/seed/62fd0b360554e/168/168",
                "background_image": "https://picsum.photos/seed/62fd0b3605556/850/350"
            },
            "data": { "id": 3, "count": 642, "updated_at": "20m" }
        },
        {
            "friend": {
                "id": 318,
                "name": "Kenyatta Windler",
                "first_name": "Kenyatta",
                "profile_image": "https://picsum.photos/seed/62fd0fe1349c3/168/168",
                "background_image": "https://picsum.photos/seed/62fd0fe1349cc/850/350"
            },
            "data": { "id": 4, "count": 9652, "updated_at": "9s" }
        },
        {
            "friend": {
                "id": 319,
                "name": "River Nolan",
                "first_name": "River",
                "profile_image": "https://picsum.photos/seed/62fd0fe1f1aef/168/168",
                "background_image": "https://picsum.photos/seed/62fd0fe1f1afb/850/350"
            },
            "data": { "id": 5, "count": 8347, "updated_at": "9s" }
        },
        {
            "friend": {
                "id": 320,
                "name": "Leonor Kautzer",
                "first_name": "Leonor",
                "profile_image": "https://picsum.photos/seed/62fd0fe336f07/168/168",
                "background_image": "https://picsum.photos/seed/62fd0fe336f14/850/350"
            },
            "data": { "id": 6, "count": 4065, "updated_at": "9s" }
        },
        {
            "friend": {
                "id": 321,
                "name": "Grayson Kessler",
                "first_name": "Grayson",
                "profile_image": "https://picsum.photos/seed/62fd0fe4221e1/168/168",
                "background_image": "https://picsum.photos/seed/62fd0fe4221f2/850/350"
            },
            "data": { "id": 7, "count": 7672, "updated_at": "9s" }
        },
        {
            "friend": {
                "id": 322,
                "name": "Brandy Considine",
                "first_name": "Brandy",
                "profile_image": "https://picsum.photos/seed/62fd0fe6b388d/168/168",
                "background_image": "https://picsum.photos/seed/62fd0fe6b3898/850/350"
            },
            "data": { "id": 8, "count": 4767, "updated_at": "9s" }
        },
        {
            "friend": {
                "id": 323,
                "name": "Yadira Kuhic",
                "first_name": "Yadira",
                "profile_image": "https://picsum.photos/seed/62fd0fe797631/168/168",
                "background_image": "https://picsum.photos/seed/62fd0fe79763a/850/350"
            },
            "data": { "id": 9, "count": 1633, "updated_at": "9s" }
        },
        {
            "friend": {
                "id": 324,
                "name": "Zechariah Krajcik",
                "first_name": "Zechariah",
                "profile_image": "https://picsum.photos/seed/62fd0fe8a6019/168/168",
                "background_image": "https://picsum.photos/seed/62fd0fe8a6048/850/350"
            },
            "data": { "id": 10, "count": 9035, "updated_at": "9s" }
        }
    ],
    "current_page": 1,
    "next_page": 2,
    "prev_page": null
}
